barracks/__init__.py
barracks/barracks.py
barracks-0.1.0.dist-info/METADATA
barracks-0.1.0.dist-info/RECORD
barracks-0.1.0.dist-info/WHEEL
barracks-0.1.0.dist-info/top_level.txt
